d2api/__init__.py
d2api/ref/abilities.json
d2api/ref/heroes.json
d2api/ref/items.json
d2api/ref/meta.json
d2api/src/__init__.py
d2api/src/endpoints.py
d2api/src/entities.py
d2api/src/errors.py
d2api/src/util.py
d2api/src/wrappers.py
d2api-1.1.dist-info/LICENSE
d2api-1.1.dist-info/METADATA
d2api-1.1.dist-info/WHEEL
d2api-1.1.dist-info/top_level.txt
d2api-1.1.dist-info/RECORD
