Metadata-Version: 2.1
Name: d2api
Version: 1.1
Summary: Dota 2 API wrapper and parser for Python 3
Home-page: https://github.com/whoophee/d2api
Author: Raghav Sairam
Author-email: raghavsairamn@gmail.com
License: GPL-3.0
Keywords: dota2 dota api d2api parser
Platform: UNKNOWN
Classifier: Intended Audience :: Developers
Classifier: Topic :: Software Development :: Libraries :: Python Modules
Classifier: Development Status :: 5 - Production/Stable
Classifier: License :: OSI Approved :: GNU General Public License (GPL)
Classifier: Programming Language :: Python
Classifier: Programming Language :: Python :: 3.3
Classifier: Programming Language :: Python :: 3.4
Classifier: Programming Language :: Python :: 3.5
Classifier: Programming Language :: Python :: 3.6
Requires-Dist: requests
